bingocpp.cpython-39-x86_64-linux-gnu.so
bingo_nasa.libs/libstdc++-496613c0.so.6.0.32
bingo_nasa.libs/libgcc_s-a3a07607.so.1
bingo_nasa-0.5.4.dist-info/METADATA
bingo_nasa-0.5.4.dist-info/top_level.txt
bingo_nasa-0.5.4.dist-info/WHEEL
bingo_nasa-0.5.4.dist-info/RECORD
bingo_nasa-0.5.4.dist-info/licenses/LICENSE.txt
bingo/__init__.py
bingo/local_optimizers/local_opt_fitness.py
bingo/local_optimizers/__init__.py
bingo/local_optimizers/scipy_optimizer.py
bingo/local_optimizers/normalized_marginal_likelihood.py
bingo/local_optimizers/smcpy_optimizer.py
bingo/local_optimizers/local_optimizer.py
bingo/symbolic_regression/equation.py
bingo/symbolic_regression/implicit_regression.py
bingo/symbolic_regression/__init__.py
bingo/symbolic_regression/equation_regressor.py
bingo/symbolic_regression/srbench_interface.py
bingo/symbolic_regression/atomic_potential_regression.py
bingo/symbolic_regression/explicit_regression.py
bingo/symbolic_regression/symbolic_regressor.py
bingo/symbolic_regression/implicit_regression_schmidt.py
bingo/symbolic_regression/agraph/string_parsing.py
bingo/symbolic_regression/agraph/operator_definitions.py
bingo/symbolic_regression/agraph/generator.py
bingo/symbolic_regression/agraph/onnx_interface.py
bingo/symbolic_regression/agraph/__init__.py
bingo/symbolic_regression/agraph/crossover.py
bingo/symbolic_regression/agraph/agraph.py
bingo/symbolic_regression/agraph/string_generation.py
bingo/symbolic_regression/agraph/component_generator.py
bingo/symbolic_regression/agraph/mutation.py
bingo/symbolic_regression/agraph/simplification_backend/__init__.py
bingo/symbolic_regression/agraph/simplification_backend/automatic_simplification.py
bingo/symbolic_regression/agraph/simplification_backend/interpreter.py
bingo/symbolic_regression/agraph/simplification_backend/optional_expression_modification.py
bingo/symbolic_regression/agraph/simplification_backend/simplification_backend.py
bingo/symbolic_regression/agraph/simplification_backend/constant_folding.py
bingo/symbolic_regression/agraph/simplification_backend/simplify.py
bingo/symbolic_regression/agraph/simplification_backend/expression.py
