Metadata-Version: 2.4
Name: bingo-nasa
Version: 0.5.4
Summary: A package for genetic optimization and symbolic regression.
Author-email: Geoffrey Bomarito <geoffrey.f.bomarito@nasa.gov>
License: 
Project-URL: Documentation, https://nasa.github.io/bingo/
Project-URL: Repository, https://github.com/nasa/bingo
Keywords: symbolic regression
Classifier: License :: OSI Approved :: Apache Software License
Classifier: Development Status :: 3 - Alpha
Classifier: Programming Language :: Python :: 3.9
Classifier: Programming Language :: Python :: 3.10
Classifier: Programming Language :: Python :: 3.11
Classifier: Programming Language :: Python :: 3.12
Requires-Python: >=3.9
License-File: LICENSE.txt
Requires-Dist: mpi4py>=4.0
Requires-Dist: numpy
Requires-Dist: scipy
Requires-Dist: dill
Requires-Dist: sympy
Requires-Dist: scikit-learn
Requires-Dist: smcpy
Requires-Dist: pybind11[global]
Provides-Extra: onnx
Requires-Dist: onnx; extra == "onnx"
Provides-Extra: tests
Requires-Dist: pytest; extra == "tests"
Requires-Dist: pytest-mock; extra == "tests"
Requires-Dist: pytest-timeout; extra == "tests"
Requires-Dist: pytest-cov; extra == "tests"
Requires-Dist: coverage; extra == "tests"
Requires-Dist: coveralls; extra == "tests"
Dynamic: license-file
